blt/__init__.py
blt/blt.cpython-313-darwin.so
blt_tokenizer-0.2.2.dist-info/METADATA
blt_tokenizer-0.2.2.dist-info/WHEEL
blt_tokenizer-0.2.2.dist-info/licenses/LICENSE
blt_tokenizer-0.2.2.dist-info/RECORD
