Metadata-Version: 2.4
Name: blt-tokenizer
Version: 0.2.2
Classifier: Development Status :: 4 - Beta
Classifier: Intended Audience :: Developers
Classifier: License :: OSI Approved :: Apache Software License
Classifier: Programming Language :: Python :: 3
Classifier: Programming Language :: Python :: 3.8
Classifier: Programming Language :: Python :: 3.9
Classifier: Programming Language :: Python :: 3.10
Classifier: Programming Language :: Python :: 3.11
Classifier: Programming Language :: Python :: 3.12
Classifier: Programming Language :: Python :: 3.13
Classifier: Programming Language :: Rust
Classifier: Topic :: Scientific/Engineering :: Artificial Intelligence
Classifier: Topic :: Text Processing
Requires-Dist: pytest>=6.0 ; extra == 'dev'
Requires-Dist: pytest-benchmark>=4.0 ; extra == 'dev'
Requires-Dist: numpy>=1.20 ; extra == 'dev'
Requires-Dist: black>=22.0 ; extra == 'dev'
Requires-Dist: isort>=5.0 ; extra == 'dev'
Requires-Dist: mypy>=0.900 ; extra == 'dev'
Provides-Extra: dev
License-File: LICENSE
Summary: High-performance byte-level tokenizer with BPE support
Keywords: tokenizer,bpe,nlp,byte-level,performance
Home-Page: https://github.com/jtrefon/blt
Author: BLT Contributors
License: Apache-2.0
Requires-Python: >=3.8
Project-URL: Source Code, https://github.com/jtrefon/blt
